{
  "main": {
    "id": "cdaee13d524ab6ec",
    "type": "split",
    "children": [
      {
        "id": "8f03956823a18b1c",
        "type": "tabs",
        "children": [
          {
            "id": "043f0a17714d03ad",
            "type": "leaf",
            "state": {
              "type": "markdown",
              "state": {
                "file": "Jonathan Inc./Journaling/oct 2025/1 oct 2025.md",
                "mode": "source",
                "source": false
              },
              "icon": "lucide-file",
              "title": "1 oct 2025"
            }
          }
        ]
      }
    ],
    "direction": "vertical"
  },
  "left": {
    "id": "8ebb31a71f1594e7",
    "type": "split",
    "children": [
      {
        "id": "8cc3a036b2390036",
        "type": "tabs",
        "children": [
          {
            "id": "6a961bfd464f9e13",
            "type": "leaf",
            "state": {
              "type": "file-explorer",
              "state": {
                "sortOrder": "alphabetical",
                "autoReveal": false
              },
              "icon": "lucide-folder-closed",
              "title": "Files"
            }
          },
          {
            "id": "3d5461d5210cbbd2",
            "type": "leaf",
            "state": {
              "type": "search",
              "state": {
                "query": "tag:#systems-thinking_",
                "matchingCase": false,
                "explainSearch": false,
                "collapseAll": false,
                "extraContext": false,
                "sortOrder": "alphabetical"
              },
              "icon": "lucide-search",
              "title": "Search"
            }
          },
          {
            "id": "d1cce5b8c19b0b3f",
            "type": "leaf",
            "state": {
              "type": "bookmarks",
              "state": {},
              "icon": "lucide-bookmark",
              "title": "Bookmarks"
            }
          },
          {
            "id": "b7e3cac91990b7b6",
            "type": "leaf",
            "state": {
              "type": "markdown",
              "state": {
                "file": "Thought Collection/Books (Single source and note)/The Tacit Dimension - M. Polanyi/The body and tools as an interface to obtaining knowledge.md",
                "mode": "source",
                "source": false
              },
              "icon": "lucide-file",
              "title": "The body and tools as an interface to obtaining knowledge"
            }
          }
        ]
      }
    ],
    "direction": "horizontal",
    "width": 355.50390243530273
  },
  "right": {
    "id": "c5901c2bc0fb577b",
    "type": "split",
    "children": [
      {
        "id": "693d59f0606a2f1c",
        "type": "tabs",
        "children": [
          {
            "id": "6eda61d0b21d228a",
            "type": "leaf",
            "state": {
              "type": "tag",
              "state": {
                "sortOrder": "frequency",
                "useHierarchy": true,
                "showSearch": false,
                "searchQuery": ""
              },
              "icon": "lucide-tags",
              "title": "Tags"
            }
          },
          {
            "id": "f419ea869367a0ce",
            "type": "leaf",
            "state": {
              "type": "outline",
              "state": {
                "file": "Thought Collection/Books (Single source and note)/We Who Wrestle with God - J. Peterson/Psyche.md"
              },
              "icon": "lucide-list",
              "title": "Outline of Psyche"
            }
          },
          {
            "id": "8e2efebd1dbe8725",
            "type": "leaf",
            "state": {
              "type": "backlink",
              "state": {
                "file": "Programming/Golang/Knowledge and Questions/EOF.md",
                "collapseAll": false,
                "extraContext": false,
                "sortOrder": "alphabetical",
                "showSearch": false,
                "searchQuery": "",
                "backlinkCollapsed": false,
                "unlinkedCollapsed": true
              },
              "icon": "links-coming-in",
              "title": "Backlinks for EOF"
            }
          },
          {
            "id": "83c8e2b93dd8ebbe",
            "type": "leaf",
            "state": {
              "type": "outgoing-link",
              "state": {
                "file": "Programming/Golang/Knowledge and Questions/EOF.md",
                "linksCollapsed": false,
                "unlinkedCollapsed": true
              },
              "icon": "links-going-out",
              "title": "Outgoing links from EOF"
            }
          }
        ],
        "currentTab": 3
      }
    ],
    "direction": "horizontal",
    "width": 408.5,
    "collapsed": true
  },
  "left-ribbon": {
    "hiddenItems": {
      "bases:Create new base": false,
      "switcher:Open quick switcher": false,
      "graph:Open graph view": false,
      "canvas:Create new canvas": false,
      "daily-notes:Open today's daily note": false,
      "templates:Insert template": false,
      "command-palette:Open command palette": false
    }
  },
  "active": "043f0a17714d03ad",
  "lastOpenFiles": [
    "Jonathan Inc./Journaling/sep 2025/29 sept 2025.md",
    "Jonathan Inc./Journaling/sep 2025/30 sept 2025.md",
    "Jonathan Inc./Journaling/oct 2025/1 oct 2025.md",
    "Jonathan Inc./Journaling/sep 2025/14 sep 2025.md",
    "Jonathan Inc./Journaling/oct 2025",
    "Thought Collection/Books (Single source and note)/The Effective Executive - P. Drucker/Categories of Problems.md",
    "Jonathan Inc./Journaling/sep 2025",
    "Thought Collection/Books (Single source and note)/The Effective Executive - P. Drucker/Build on the Strength of your Boss.md",
    "Thought Collection/Books (Single source and note)/The Effective Executive - P. Drucker/The Effective Executive.md",
    "Thought Collection/Books (Single source and note)/The Effective Executive - P. Drucker/Effective Decisions.md",
    "Thought Collection/Books (Single source and note)/The Effective Executive - P. Drucker/Concentration and Proper Aim.md",
    "Jonathan Inc./Tools/Mental models/Mental Models & Frameworks.md",
    "Jonathan Inc./Journaling/sep 2025/20 sept 2025.md",
    "Jonathan Inc./Journaling/sep 2025/25 sept 2025.md",
    "Thought Collection/Books (Single source and note)/Creativity Flow and the Psychology of Discovery and Invention - M. Csikszentmihalyi/The Systems Model of Creativity.md",
    "Thought Collection/Books (Single source and note)/Creativity Flow and the Psychology of Discovery and Invention - M. Csikszentmihalyi/The Limited Supply of Attention.md",
    "Thought Collection/Books (Single source and note)/Creativity Flow and the Psychology of Discovery and Invention - M. Csikszentmihalyi/Foundations of Creative Life.md",
    "Thought Collection/Books (Single source and note)/Creativity Flow and the Psychology of Discovery and Invention - M. Csikszentmihalyi/Creativity - Individual vs Systematic.md",
    "Thought Collection/Books (Single source and note)/Creativity Flow and the Psychology of Discovery and Invention - M. Csikszentmihalyi/Complex systems.md",
    "Jonathan Inc./Journaling/sep 2025/28 sept 2025.md",
    "Jonathan Inc./Journaling/sep 2025/27 sept 2025.md",
    "Jonathan Inc./Journaling/sep 2025/24 sept 2025.md",
    "Jonathan Inc./Journaling/sep 2025/22 sept 2025.md",
    "Untitled 4.md",
    "Jonathan Inc./Journaling/sep 2025/21 sept 2025.md",
    "Untitled 3.md",
    "Jonathan Inc./Journaling/sep 2025/19 sept 2025.md",
    "Jonathan Inc./Journaling/sep 2025/18 sep 2025.md",
    "Jonathan Inc./Journaling",
    "Jonathan Inc./Projects/0. Ideas/Projects",
    "Thought Collection/Books (Single source and note)/The Effective Executive - P. Drucker",
    "Thought Collection/Books (Single source and note)/Curious - I.Leslie/Synthesizing.canvas",
    "Thought Collection/Books (Single source and note)/A More Beautiful Question - W. Berger",
    "Thought Collection/Books (Single source and note)/Untitled.canvas",
    "Pasted image 20250720121141.png",
    "Pictures/Pasted image 20250715124017.png",
    "curiousityknowledge 1.jpg",
    "Pictures/Pasted image 20250715123650.png",
    "Pictures/Pasted image 20250715123626.png",
    "curiousityknowledge.jpg",
    "Thought Collection/Todos and Drafts/Raw Source Extracts",
    "Thought Collection/Books (Single source and note)/Nätokraterna - A. Bard, J. Söderqvist",
    "Thought Collection/Books (Single source and note)/The Tacit Dimension - M.Polanyi",
    "Thought Collection/Books (Single source and note)/Creativity Flow and the Psychology of Discovery and Invention - M. Csikszentmihalyi",
    "Pictures/Pasted image 20250715123956.png",
    "Pictures/Pasted image 20241223180817.png",
    "Pictures/Skärmavbild 2025-06-29 kl. 11.28.24.png",
    "Pictures/Pasted image 20241224214721.png",
    "Programming/Algorithms/Canvas of important algorithms.canvas"
  ]
}